AITrafficLab/__init__.py
AITrafficLab/agents.py
AITrafficLab/batch.py
AITrafficLab/connection.py
AITrafficLab/error_codes.py
AITrafficLab/generators.py
AITrafficLab/ootraci.py
AITrafficLab/schedule.py
AITrafficLab/traffic_model.py
AITrafficLab/algorithms/__init__.py
AITrafficLab/algorithms/iaco.py
AITrafficLab/algorithms/iaco_train.py
AITrafficLab/algorithms/ipr.py
AITrafficLab/algorithms/siaco.py
AITrafficLab/algorithms/siaco_train.py
AITrafficLab-0.3.dist-info/LICENSE
AITrafficLab-0.3.dist-info/METADATA
AITrafficLab-0.3.dist-info/WHEEL
AITrafficLab-0.3.dist-info/top_level.txt
AITrafficLab-0.3.dist-info/RECORD
